neuralcompression/__init__.py
neuralcompression/version.py
neuralcompression/_outputs/__init__.py
neuralcompression/_outputs/_discriminator_output.py
neuralcompression/_outputs/_hyperprior_output.py
neuralcompression/_outputs/_vqvae_autoencoder_output.py
neuralcompression/data/__init__.py
neuralcompression/data/_clic_2020_image.py
neuralcompression/data/_clic_2020_video.py
neuralcompression/data/_div2k_dataset.py
neuralcompression/data/_kodak.py
neuralcompression/data/_openimages_v6.py
neuralcompression/data/_vimeo_90k_septuplet.py
neuralcompression/distributions/__init__.py
neuralcompression/distributions/_noisy_normal.py
neuralcompression/distributions/_uniform_noise.py
neuralcompression/functional/__init__.py
neuralcompression/functional/_count_flops.py
neuralcompression/functional/_dense_image_warp.py
neuralcompression/functional/_estimate_tails.py
neuralcompression/functional/_hsv_to_rgb.py
neuralcompression/functional/_image_to_255_scale.py
neuralcompression/functional/_information_content.py
neuralcompression/functional/_log_cdf.py
neuralcompression/functional/_log_expm1.py
neuralcompression/functional/_log_ndtr.py
neuralcompression/functional/_log_survival_function.py
neuralcompression/functional/_lower_bound.py
neuralcompression/functional/_lower_tail.py
neuralcompression/functional/_lpips.py
neuralcompression/functional/_multiscale_structural_similarity.py
neuralcompression/functional/_ndtr.py
neuralcompression/functional/_optical_flow_to_color.py
neuralcompression/functional/_pad_image.py
neuralcompression/functional/_quantization_offset.py
neuralcompression/functional/_soft_round.py
neuralcompression/functional/_soft_round_conditional_mean.py
neuralcompression/functional/_soft_round_inverse.py
neuralcompression/functional/_survival_function.py
neuralcompression/functional/_upper_tail.py
neuralcompression/layers/__init__.py
neuralcompression/layers/_channel_norm.py
neuralcompression/layers/_continuous_entropy.py
neuralcompression-0.3.1.dist-info/LICENSE
neuralcompression-0.3.1.dist-info/METADATA
neuralcompression-0.3.1.dist-info/WHEEL
neuralcompression-0.3.1.dist-info/top_level.txt
neuralcompression-0.3.1.dist-info/RECORD
