Metadata-Version: 2.1
Name: neuralcompression
Version: 0.3.1
Summary: A collection of tools for neural compression enthusiasts
Home-page: https://github.com/facebookresearch/NeuralCompression
Author: Facebook AI Research
License: MIT
Classifier: Programming Language :: Python :: 3
Classifier: Programming Language :: Python :: 3.8
Classifier: License :: OSI Approved :: MIT License
Classifier: Operating System :: OS Independent
Classifier: Development Status :: 3 - Alpha
Classifier: Intended Audience :: Developers
Classifier: Topic :: Scientific/Engineering :: Artificial Intelligence
Classifier: Topic :: System :: Archiving :: Compression
Requires-Python: >=3.10
License-File: LICENSE
Requires-Dist: compressai >=1.2.4
Requires-Dist: DISTS-pytorch >=0.1
Requires-Dist: fvcore >=0.1.5.post20211023
Requires-Dist: lpips >=0.1.4
Requires-Dist: pillow >=9.4.0
Requires-Dist: pytorchvideo >=0.1.5
Requires-Dist: scipy <=1.11.1
Requires-Dist: torch >=2.0.1
Requires-Dist: torch-fidelity >=0.3.0
Requires-Dist: torchmetrics >=1.1.0
Requires-Dist: torchvision >=0.15.2
Requires-Dist: tqdm >=4.66.1
Provides-Extra: dev
Requires-Dist: black >=23.7.0 ; extra == 'dev'
Requires-Dist: flake8 >=6.1.0 ; extra == 'dev'
Requires-Dist: isort >=5.12.0 ; extra == 'dev'
Requires-Dist: mypy >=1.5.1 ; extra == 'dev'
Requires-Dist: pytest >=7.4.0 ; extra == 'dev'
Provides-Extra: docs
Requires-Dist: myst-parser >=0.15.2 ; extra == 'docs'
Requires-Dist: sphinx-autodoc-typehints >=1.12.0 ; extra == 'docs'
Requires-Dist: sphinx-copybutton >=0.4.0 ; extra == 'docs'
Requires-Dist: sphinx-gallery >=0.10.1 ; extra == 'docs'
Requires-Dist: sphinx-rtd-theme >=1.0.0 ; extra == 'docs'
Requires-Dist: sphinxcontrib-katex >=0.8.6 ; extra == 'docs'
Requires-Dist: sphinx >=4.3.1 ; extra == 'docs'
Provides-Extra: tests
Requires-Dist: black ==23.7.0 ; extra == 'tests'
Requires-Dist: compressai ==1.2.4 ; extra == 'tests'
Requires-Dist: flake8 ==6.1.0 ; extra == 'tests'
Requires-Dist: fvcore ==0.1.5.post20221221 ; extra == 'tests'
Requires-Dist: isort ==5.12.0 ; extra == 'tests'
Requires-Dist: lpips ==0.1.4 ; extra == 'tests'
Requires-Dist: mypy ==1.5.1 ; extra == 'tests'
Requires-Dist: opencv-python ~=4.8.0.76 ; extra == 'tests'
Requires-Dist: pillow ==9.4.0 ; extra == 'tests'
Requires-Dist: pytest ==7.4.0 ; extra == 'tests'
Requires-Dist: pytorchvideo ==0.1.5 ; extra == 'tests'
Requires-Dist: scipy ==1.11.1 ; extra == 'tests'
Requires-Dist: torch ==2.0.1 ; extra == 'tests'
Requires-Dist: torchmetrics ==1.1.0 ; extra == 'tests'
Requires-Dist: torchvision ==0.15.2 ; extra == 'tests'
